{
  "ID": "Sr.peloIsIncredible",
  "Name": "Sr.peloIsIncredible",
  "StoreName": "Sr.peloIsIncredible",
  "HatInFrontGlobally": false,
  "NoHatBobbingGlobally": false,
  "UsePointFilteringGlobally": false,
  "UseColorFilteringGlobally": false,
  "RelatedSkin": "",
  "RelatedHat": "",
  "UsePercentageBasedPivot": true,
  "FrameList": [
    {
      "Position": {
        "x": 0.0,
        "y": 0.0
      },
      "Size": {
        "x": 200.0,
        "y": 200.0
      },
      "Offset": {
        "x": 0.420000017,
        "y": 0.799999952
      },
      "Name": "Normal",
      "SpritePath": "Skidd.png",
      "Hat_NoBobbing": false,
      "InFront": true,
      "UsePointFiltering": false,
      "UseColorFiltering": false
    },
    {
      "Position": {
        "x": 0.0,
        "y": 0.0
      },
      "Size": {
        "x": 1.0,
        "y": 1.0
      },
      "Offset": {
        "x": 0.33,
        "y": 0.85
      },
      "Name": "Floor",
      "SpritePath": "wooyari_dead.png",
      "Hat_NoBobbing": false,
      "InFront": false,
      "UsePointFiltering": false,
      "UseColorFiltering": false
    }
  ]
}