{
	"ID": "CarJem the Hedgefox",
	"NormalImg": "CarJemHat.png",
	"FloorImg": "CarJemHat.png",
	"PreviewImg": "CarJemHat.png",
	"NormalPosX": 0,
	"NormalPosY": 0,
	"NormalWidth": 84,
	"NormalHeight": 86,
	"NormalPivotX": 0.43,
	"NormalPivotY": 0.90,
	"FloorPosX": 0,
	"FloorPosY": 0,
	"FloorWidth": 84,
	"FloorHeight": 86,
	"FloorPivotX": 0.5,
	"FloorPivotY": 0.5,
	"PreviewPosX": 0,
	"PreviewPosY": 0,
	"PreviewWidth": 84,
	"PreviewHeight": 86,
	"PreviewPivotX": 0.5,
	"PreviewPivotY": 0.5,
	"inFront": "true"
}